Metadata-Version: 2.1
Name: pixabay.py
Version: 0.0.1
Summary: A pixabay API wrapper.
Home-page: https://github.com/obl1que/pixabay.py
Author: Obliquee
Author-email: jfagg19@icloud.com
License: UNKNOWN
Platform: UNKNOWN
Classifier: Programming Language :: Python :: 3
Requires-Python: >=3.6
